tfrq.py
tfrq-2.0.94.dist-info/LICENSE
tfrq-2.0.94.dist-info/METADATA
tfrq-2.0.94.dist-info/WHEEL
tfrq-2.0.94.dist-info/top_level.txt
tfrq-2.0.94.dist-info/RECORD
