Metadata-Version: 2.1
Name: tfrq
Version: 2.0.94
Summary: A library to parallelize the execution of a function in python
Author: Foad Abo Dahood
Author-email: Foad.ad5491@gmail.com
License-File: LICENSE
Requires-Dist: futures (==2.2.0)
Requires-Dist: tqdm
